LICENSE
README.md
setup.py
src/genomic_benchmarks/__init__.py
src/genomic_benchmarks.egg-info/PKG-INFO
src/genomic_benchmarks.egg-info/SOURCES.txt
src/genomic_benchmarks.egg-info/dependency_links.txt
src/genomic_benchmarks.egg-info/requires.txt
src/genomic_benchmarks.egg-info/top_level.txt
src/genomic_benchmarks/data_check/__init__.py
src/genomic_benchmarks/data_check/info.py
src/genomic_benchmarks/dataset_getters/__init__.py
src/genomic_benchmarks/dataset_getters/pytorch_datasets.py
src/genomic_benchmarks/dataset_getters/utils.py
src/genomic_benchmarks/loc2seq/__init__.py
src/genomic_benchmarks/loc2seq/cloud_caching.py
src/genomic_benchmarks/loc2seq/loc2seq.py
src/genomic_benchmarks/models/__init__.py
src/genomic_benchmarks/models/tf.py
src/genomic_benchmarks/models/torch.py
src/genomic_benchmarks/seq2loc/__init__.py
src/genomic_benchmarks/seq2loc/seq2loc.py
src/genomic_benchmarks/utils/__init__.py
src/genomic_benchmarks/utils/datasets.py
src/genomic_benchmarks/utils/paths.py