Metadata-Version: 2.1
Name: genomic-benchmarks
Version: 0.0.8
Summary: Genomic Benchmarks
Home-page: https://github.com/ML-Bioinfo-CEITEC/genomic_benchmarks
Author: RBP Bioinformatics
Author-email: ML.Bioinfo.CEITEC@gmail.com
License: Apache License 2.0
Keywords: bioinformatics,genomics,data
Platform: UNKNOWN
Classifier: Development Status :: 3 - Alpha
Classifier: Intended Audience :: Developers
Classifier: Topic :: Software Development :: Build Tools
Classifier: License :: OSI Approved :: MIT License
Classifier: Programming Language :: Python :: 3.8
Classifier: Programming Language :: Python :: 3.9
Classifier: Programming Language :: Python :: 3.10
License-File: LICENSE
